akatool/__init__.py
akatool/__main__.py
akatool/confapp.py
akatool-0.0.5.dist-info/LICENSE
akatool-0.0.5.dist-info/METADATA
akatool-0.0.5.dist-info/WHEEL
akatool-0.0.5.dist-info/top_level.txt
akatool-0.0.5.dist-info/RECORD
